flyhash/FlyHash.py
flyhash/__init__.py
FlyHash-1.1.1.dist-info/LICENSE.txt
FlyHash-1.1.1.dist-info/METADATA
FlyHash-1.1.1.dist-info/WHEEL
FlyHash-1.1.1.dist-info/top_level.txt
FlyHash-1.1.1.dist-info/RECORD
