Metadata-Version: 2.1
Name: FlyHash
Version: 1.1.1
Summary: A novel hashing algorithm based on "A neural algorithm for a fundamental computing problem" by S. Dasgupta, C. F. Stevens, and S. Navlakha (2017)
Home-page: https://github.com/TeddyHuang-00/FlyHash
Author: TeddyHuang-00
Author-email: teddyhuangnan@gmail.com
License: MIT
Project-URL: Documentation, https://flyhash.readthedocs.io/en/latest/
Project-URL: Source, https://github.com/TeddyHuang-00/FlyHash/
Project-URL: Changelog, https://flyhash.readthedocs.io/en/latest/changelog.html
Platform: any
Classifier: Development Status :: 4 - Beta
Classifier: Programming Language :: Python
Requires-Python: <3.12,>=3.7
License-File: LICENSE.txt
Requires-Dist: numpy (<2.0.0,>=1.19.5)
Requires-Dist: scipy (<2.0.0,>=1.6.0)
Requires-Dist: importlib-metadata ; python_version < "3.8"
Provides-Extra: testing
Requires-Dist: setuptools ; extra == 'testing'
Requires-Dist: pytest ; extra == 'testing'
Requires-Dist: pytest-cov ; extra == 'testing'
